CHANGES.txt
README.txt
bootstrap.py
buildout.cfg
setup.py
src/z3c/__init__.py
src/z3c.jsonrpcproxy.egg-info/PKG-INFO
src/z3c.jsonrpcproxy.egg-info/SOURCES.txt
src/z3c.jsonrpcproxy.egg-info/dependency_links.txt
src/z3c.jsonrpcproxy.egg-info/namespace_packages.txt
src/z3c.jsonrpcproxy.egg-info/not-zip-safe
src/z3c.jsonrpcproxy.egg-info/requires.txt
src/z3c.jsonrpcproxy.egg-info/top_level.txt
src/z3c/jsonrpcproxy/SETUP.cfg
src/z3c/jsonrpcproxy/__init__.py
src/z3c/jsonrpcproxy/browser.py
src/z3c/jsonrpcproxy/browser.zcml
src/z3c/jsonrpcproxy/configure.zcml
src/z3c/jsonrpcproxy/layer.py
src/z3c/jsonrpcproxy/z3c.jsonrpcproxy-configure.zcml
src/z3c/jsonrpcproxy/js/z3c.jsonrpcproxy-0.5.0.js